MANIFEST.in
README
setup.py
lib4d_sql/base64.c
lib4d_sql/base64.h
lib4d_sql/communication.c
lib4d_sql/fourd.c
lib4d_sql/fourd.h
lib4d_sql/fourd_int.h
lib4d_sql/fourd_interne.c
lib4d_sql/fourd_result.c
lib4d_sql/fourd_type.c
lib4d_sql/fourd_type.h
lib4d_sql/sqlstate.c
lib4d_sql/utils.c
lib4d_sql/utils.h
p4d/__init__.py
p4d/p4d.py
p4d/py_fourd.h
p4d.egg-info/PKG-INFO
p4d.egg-info/SOURCES.txt
p4d.egg-info/dependency_links.txt
p4d.egg-info/not-zip-safe
p4d.egg-info/requires.txt
p4d.egg-info/top_level.txt
p4d/__pycache__/_Py4d_cffi_b6bfd2f5xdcaacb94.c